[{"header":["Proposals"],"rows":[["DAO Launch","5/24/2021","7/14/2024"],["Proposals created",2437]]},{"header":["Proposals by Status","Amount","Percentage"],"rows":[["active",2,"0.08%"],["enacted",635,"26.06%"],["finished",3,"0.12%"],["passed",419,"17.19%"],["rejected",1375,"56.42%"]]},{"header":["Proposals by Type","Amount","Percentage"],"rows":[["poi",494,"20.27%"],["catalyst",2,"0.08%"],["ban_name",83,"3.41%"],["linked_wearables",79,"3.24%"],["poll",860,"35.29%"],["draft",117,"4.80%"],["governance",95,"3.90%"],["grant",649,"26.63%"],["bid",15,"0.62%"]]},{"header":["VP sources","Members","VP Amount","VP percentage"],"rows":[["totalVP","",91793574],["manaVP",2861,19988351,"21.78%"],["landVP",658,9792000,"10.67%"],["namesVP",2081,1575800,"1.72%"],["delegatedVP",123,39899412,"43.47%"],["l1WearablesVP",763,676011,"0.74%"],["rentalVP",25,534000,"0.58%"],["estateVP",287,19328000,"21.06%"]]},{"header":["VP Distribution","Members","Members Percentage","Total VP","VP percentage"],"rows":[["Total Members",4664,"",91793574],["Members w/ >=1M VP",18,"0.39%",56701001,"61.77%"],["Members w/ >=100k VP",78,"1.67%",23660187,"25.78%"],["Members w/ >=10k VP",267,"5.72%",8333713,"9.08%"],["Members w/ >=1k VP",808,"17.32%",2725136,"2.97%"],["Members w/ <1k VP",3493,"74.89%",373537,"0.41%"]]},{"header":["Delegated VP Distribution","Amount","VP percentage"],"rows":[["manaVP",1094025,"11.51%"],["landVP",1422000,"14.96%"],["estateVP",6258000,"65.82%"],["namesVP",375600,"3.95%"],["l1WearablesVP",152412,"1.60%"],["rentalVP",206000,"2.17%"],["Total Delegated VP",9508037]]},{"header":["Participation"],"rows":[["Active members",4664],["Total Votes",83475],["Max votes in a proposal",385],["Max VP in a proposal",27635861],["Median votes per proposal",55],["Avg votes per proposal",69],["Median VP per proposal",2302019],["Avg VP per proposal",3956451]]},{"header":["Projects","Amount","Percentage"],"rows":[["Projects Submitted",229],["active",0,"0.00%"],["enacted",228,"99.56%"],["finished",0,"0.00%"],["passed",1,"0.44%"],["rejected",0,"0.00%"],["Total Funds Granted",14219439]]},{"header":["Balance Summary","Total USD"],"rows":[["Aragon Agent - Ethereum","15857081.09"],["DAO Committee - Ethereum","636794.07"],["DAO Committee - Polygon","700764.56"]]},{"header":["Transactions","Amount","Total USD"],"rows":[["Total Txs",4324,6392468.306693079],["Total In",4185,1252292.9142635209],["Total Out",137,2688430.9924295614],["Total Internal",2,2451744.4]]},{"header":["Out txs fees","Number of transactions","Total USD","Average USD per transaction"],"rows":[["This month (Jul)",3,"7.44","2.48"],["Last 30 days",12,"70.14","5.84"],["Last 60 days",21,"147.13","7.01"],["Last 6 months",75,"1178.44","15.71"],["Last year",81,"1209.93","14.94"]]},{"header":["Income Sources","Amount","Total USD"],"rows":[["NAME fee :: MINT",673,"30013.24"],["MATIC Marketplace",2791,"664.42"],["Secondary Sale :: LAND fee",167,"3640.94"],["Land Rental Fee",23,"18.62"],["OTHER",118,"630400.88"],["Curation Fee",162,"37972.76"],["Secondary Sale :: ESTATE fee",79,"7521.61"],["ESTATE fee :: BID",21,"1851.52"],["Secondary Sale :: Wearable L1 fee",18,"104.79"],["ETH Marketplace",5,"66.34"],["LAND fee :: BID",13,"228.95"],["Revocations Committee Compensation",9,"629.93"],["Grant Refund/Revoke",9,"301657.06"],["DAO Committee Payment",8,"281.52"],["OpenSea",66,"382.00"],["DAO Committee Member",2,"200.79"],["Swap",21,"236657.55"]]},{"header":["Expenses Destinations","Amount","Total USD"],"rows":[["Community Grant",20,"795117.74"],["Curator",38,"13329.33"],["DAO Committee Payment",21,"49241.15"],["OTHER",36,"1122728.42"],["Revocations Committee Compensation",15,"2974.47"],["Bid",2,"197832.23"],["Operational Grant",2,"204683.52"],["Secondary Sale",1,"65505.98"],["DAO Committee Member",1,"2435.25"],["Swap",1,"234582.90"]]}]