[{"header":["Proposals"],"rows":[["DAO Launch","5/24/2021","11/2/2023"],["Proposals created",2086]]},{"header":["Proposals by Status","Amount","Percentage"],"rows":[["active",14,"0.67%"],["enacted",550,"26.37%"],["finished",1,"0.05%"],["passed",306,"14.67%"],["rejected",1211,"58.05%"]]},{"header":["Proposals by Type","Amount","Percentage"],"rows":[["ban_name",81,"3.88%"],["draft",83,"3.98%"],["governance",72,"3.45%"],["grant",585,"28.04%"],["linked_wearables",76,"3.64%"],["poi",431,"20.66%"],["poll",731,"35.04%"],["catalyst",2,"0.10%"]]},{"header":["VP sources","Members","VP Amount","VP percentage"],"rows":[["totalVP","",100089036],["manaVP",2926,33466484,"33.44%"],["landVP",647,9824000,"9.82%"],["namesVP",2005,1508300,"1.51%"],["delegatedVP",119,35255259,"35.22%"],["l1WearablesVP",750,648993,"0.65%"],["rentalVP",30,762000,"0.76%"],["estateVP",291,18624000,"18.61%"]]},{"header":["VP Distribution","Members","Members Percentage","Total VP","VP percentage"],"rows":[["Total Members",4468,"",100089036],["Members w/ >=1M VP",19,"0.43%",50755887,"50.71%"],["Members w/ >=100k VP",100,"2.24%",37736207,"37.70%"],["Members w/ >=10k VP",267,"5.98%",8477212,"8.47%"],["Members w/ >=1k VP",810,"18.13%",2745357,"2.74%"],["Members w/ <1k VP",3272,"73.23%",374375,"0.37%"]]},{"header":["Delegated VP Distribution","Amount","VP percentage"],"rows":[["manaVP",1393801,"18.97%"],["landVP",1018000,"13.86%"],["estateVP",4272000,"58.15%"],["namesVP",338200,"4.60%"],["l1WearablesVP",108825,"1.48%"],["rentalVP",216000,"2.94%"],["Total Delegated VP",7346826]]},{"header":["Participation"],"rows":[["Active members",4468],["Total Votes",71809],["Max votes in a proposal",385],["Max VP in a proposal",24274601],["Median votes per proposal",53],["Avg votes per proposal",70],["Median VP per proposal",1707096],["Avg VP per proposal",3498983]]},{"header":["Grants","Amount","Percentage"],"rows":[["Grants Submitted",585],["active",3,"0.51%"],["enacted",199,"34.02%"],["finished",0,"0.00%"],["passed",0,"0.00%"],["rejected",380,"64.96%"],["Total Funds Granted",12639888]]},{"header":["Balance Summary","Total USD"],"rows":[["Aragon Agent - Ethereum","19357698.61"],["DAO Committee - Ethereum","1248229.72"],["DAO Committee - Polygon","849249.17"]]},{"header":["Transactions","Amount","Total USD"],"rows":[["Total Txs",21050,42393097.30887429],["Total In",20745,18895394.48580266],["Total Out",235,10714251.55623995],["Total Internal",70,12783451.266831573]]},{"header":["Out txs fees","Number of transactions","Total USD","Average USD per transaction"],"rows":[["This month (Nov)",0,"0.00",0],["Last 30 days",21,"124.52","5.93"],["Last 60 days",41,"217.99","5.32"],["Last 6 months",108,"866.63","8.02"],["Last year",155,"1114.28","7.19"]]},{"header":["Income Sources","Amount","Total USD"],"rows":[["MATIC Marketplace",16770,"2638.03"],["NAME fee :: MINT",1239,"45643.89"],["Curation Fee",890,"250320.69"],["Secondary Sale :: LAND fee",390,"17147.39"],["Secondary Sale :: ESTATE fee",109,"17934.60"],["OpenSea",666,"10434.59"],["Land Rental Fee",140,"1153.16"],["OTHER",27,"1333495.75"],["Grant Refund/Revoke",15,"731273.80"],["Secondary Sale :: Wearable L1 fee",42,"64.75"],["Swap",287,"2533513.85"],["ESTATE fee :: BID",70,"22791.25"],["DAO Committee Member",11,"953823.86"],["DAO Committee Payment",3,"146.03"],["LAND fee :: BID",42,"2402.74"],["Wearable L1 fee :: BID",1,"27.38"],["NAME fee :: BID",9,"28.09"],["Secondary Sale :: NAME fee",8,"54.88"],["Revocations Committee Compensation",1,"286.53"],["Vesting Contract",1,"12972029.57"],["LooksRare",24,"183.66"]]},{"header":["Expenses Destinations","Amount","Total USD"],"rows":[["Grant",75,"5142916.01"],["OTHER",28,"1770020.79"],["Revocations Committee Compensation",6,"1807.43"],["Swap",16,"2582620.41"],["ETH Marketplace",28,"69172.09"],["Curator",48,"78263.54"],["DAO Committee Payment",16,"37338.99"],["DAO Committee Member",14,"978543.11"],["Secondary Sale",4,"53569.19"]]}]