[{"header":["Proposals"],"rows":[["DAO Launch","5/24/2021","6/8/2023"],["Proposals created",1755]]},{"header":["Proposals by Status","Amount","Percentage"],"rows":[["active",12,"0.68%"],["enacted",468,"26.67%"],["finished",0,"0.00%"],["passed",235,"13.39%"],["rejected",1040,"59.26%"]]},{"header":["Proposals by Type","Amount","Percentage"],"rows":[["ban_name",64,"3.65%"],["draft",55,"3.13%"],["governance",49,"2.79%"],["grant",488,"27.81%"],["linked_wearables",73,"4.16%"],["poi",402,"22.91%"],["poll",621,"35.38%"],["catalyst",2,"0.11%"]]},{"header":["VP sources","Members","VP Amount","VP percentage"],"rows":[["totalVP","",91518001],["manaVP",2786,32868819,"35.92%"],["landVP",783,30636000,"33.48%"],["namesVP",1870,1420700,"1.55%"],["delegatedVP",95,25217522,"27.55%"],["l1WearablesVP",720,610960,"0.67%"],["rentalVP",28,764000,"0.83%"]]},{"header":["VP Distribution","Members","Members Percentage","Total VP","VP percentage"],"rows":[["Total Members",4199,"",91518001],["Members w/ >=1M VP",18,"0.43%",48969110,"53.51%"],["Members w/ >=100k VP",84,"2.00%",31452010,"34.37%"],["Members w/ >=10k VP",257,"6.12%",8113103,"8.87%"],["Members w/ >=1k VP",780,"18.58%",2619026,"2.86%"],["Members w/ <1k VP",3060,"72.87%",364752,"0.40%"]]},{"header":["Delegated VP Distribution","Amount","VP percentage"],"rows":[["manaVP",796335,"11.88%"],["landVP",5298000,"79.04%"],["namesVP",291000,"4.34%"],["l1WearablesVP",103670,"1.55%"],["rentalVP",214000,"3.19%"],["Total Delegated VP",6703005]]},{"header":["Participation"],"rows":[["Active members",4199],["Total Votes",56429],["Max votes in a proposal",385],["Max VP in a proposal",20950876],["Median votes per proposal",38],["Avg votes per proposal",62],["Median VP per proposal",1228552],["Avg VP per proposal",2459541]]},{"header":["Grants","Amount","Percentage"],"rows":[["Grants Submitted",488],["active",6,"1.23%"],["enacted",162,"33.20%"],["finished",0,"0.00%"],["passed",3,"0.61%"],["rejected",317,"64.96%"],["Total Funds Granted",10238219]]},{"header":["Balance Summary","Total USD"],"rows":[["Aragon Agent - Ethereum","22513661.22"],["DAO Committee - Ethereum","764411.47"],["DAO Committee - Polygon","797667.29"]]},{"header":["Transactions","Amount","Total USD"],"rows":[["Total Txs",163793,155584744.5657243],["Total In",163234,82029772.04291412],["Total Out",477,27288473.70854982],["Total Internal",82,46266498.81425816]]},{"header":["Out txs fees","Number of transactions","Total USD","Average USD per transaction"],"rows":[["This month (Jun)",10,"133.84","13.38"],["Last 30 days",21,"280.93","13.38"],["Last 60 days",27,"342.92","12.70"],["Last 6 months",79,"570.02","7.22"],["Last year",136,"1367.72","10.06"]]},{"header":["Income Sources","Amount","Total USD"],"rows":[["MATIC Marketplace",133625,"37507.90"],["NAME fee :: MINT",165,"8782.96"],["Swap",188,"11122052.72"],["Curation Fee",4482,"2081879.54"],["Secondary Sale :: Wearable L1 fee",896,"7936.99"],["OTHER",249,"3234296.46"],["Secondary Sale :: LAND fee",5770,"1470719.22"],["Grant Refund/Revoke",16,"274214.61"],["LAND fee :: BID",380,"82285.32"],["Secondary Sale :: ESTATE fee",1095,"1259666.83"],["ESTATE fee :: BID",439,"780921.09"],["OpenSea",15450,"364895.52"],["NAME fee :: BID",15,"341.94"],["Vesting Contract",7,"60934495.11"],["LooksRare",80,"38514.22"],["Secondary Sale :: NAME fee",362,"6831.87"],["DAO Committee Member",4,"70686.64"],["Wearable L1 fee :: BID",10,"175.92"],["SAB DCL",1,"253567.21"]]},{"header":["Expenses Destinations","Amount","Total USD"],"rows":[["Grant",178,"11342545.94"],["OTHER",70,"4053543.31"],["ETH Marketplace",5,"18291.58"],["Swap",63,"11398774.72"],["DAO Committee Member",9,"79112.28"],["Secondary Sale",2,"17210.46"],["Curator",142,"344868.56"],["Facilitator",8,"34126.87"]]}]